IosIapJiaocheng/README.md
IosIapJiaocheng/__init__.py
IosIapJiaocheng/__main__.py
IosIapJiaocheng/file.epub
IosIapJiaocheng/index.html
IosIapJiaocheng/css/__init__.py
IosIapJiaocheng/css/annotations.css
IosIapJiaocheng/css/main.css
IosIapJiaocheng/css/normalize.css
IosIapJiaocheng/css/popup.css
IosIapJiaocheng/font/__init__.py
IosIapJiaocheng/font/fontello.eot
IosIapJiaocheng/font/fontello.svg
IosIapJiaocheng/font/fontello.ttf
IosIapJiaocheng/font/fontello.woff
IosIapJiaocheng/img/__init__.py
IosIapJiaocheng/img/annotator-glyph-sprite.png
IosIapJiaocheng/img/annotator-icon-sprite.png
IosIapJiaocheng/img/apple-touch-icon.png
IosIapJiaocheng/img/cancelfullscreen.png
IosIapJiaocheng/img/close.png
IosIapJiaocheng/img/fullscreen.png
IosIapJiaocheng/img/loader.gif
IosIapJiaocheng/img/menu-icon.png
IosIapJiaocheng/img/save.png
IosIapJiaocheng/img/saved.png
IosIapJiaocheng/img/settings-s.png
IosIapJiaocheng/img/settings.png
IosIapJiaocheng/img/star.png
IosIapJiaocheng/js/__init__.py
IosIapJiaocheng/js/epub.js
IosIapJiaocheng/js/epub.min.js
IosIapJiaocheng/js/epub.min.map
IosIapJiaocheng/js/hooks.min.js
IosIapJiaocheng/js/hooks.min.map
IosIapJiaocheng/js/reader.js
IosIapJiaocheng/js/reader.js.map
IosIapJiaocheng/js/reader.min.js
IosIapJiaocheng/js/reader.min.map
IosIapJiaocheng/js/hooks/__init__.py
IosIapJiaocheng/js/hooks/extensions/__init__.py
IosIapJiaocheng/js/hooks/extensions/highlight.js
IosIapJiaocheng/js/libs/__init__.py
IosIapJiaocheng/js/libs/jquery.min.js
IosIapJiaocheng/js/libs/localforage.min.js
IosIapJiaocheng/js/libs/screenfull.js
IosIapJiaocheng/js/libs/screenfull.min.js
IosIapJiaocheng/js/libs/zip.min.js
IosIapJiaocheng/js/plugins/__init__.py
IosIapJiaocheng/js/plugins/hypothesis.js
IosIapJiaocheng/js/plugins/search.js
ios_iap_jiaocheng-2024.3.4.0.dist-info/METADATA
ios_iap_jiaocheng-2024.3.4.0.dist-info/WHEEL
ios_iap_jiaocheng-2024.3.4.0.dist-info/entry_points.txt
ios_iap_jiaocheng-2024.3.4.0.dist-info/top_level.txt
ios_iap_jiaocheng-2024.3.4.0.dist-info/RECORD
